isodesign/__init__.py
isodesign/__main__.py
isodesign/base/__init__.py
isodesign/base/isotopomer.py
isodesign/base/label_input.py
isodesign/base/process.py
isodesign/base/score.py
isodesign/last_version.txt
isodesign/tests/__init__.py
isodesign/tests/conftest.py
isodesign/tests/test_process.py
isodesign/ui/__init__.py
isodesign/ui/Load_data.py
isodesign/ui/pages/2_Define_label_inputs.py
isodesign/ui/pages/3_Run_simulations.py
isodesign/ui/pages/4_Analyze_results.py
isodesign-2.0.3.dist-info/entry_points.txt
isodesign-2.0.3.dist-info/LICENSE
isodesign-2.0.3.dist-info/METADATA
isodesign-2.0.3.dist-info/WHEEL
isodesign-2.0.3.dist-info/RECORD
