Metadata-Version: 2.1
Name: isodesign
Version: 2.0.3
Summary: Facilitates the choice of the optimal isotopic composition of labeled substrates in 13C-fluxomics experiments.
Author: rkouakou
Author-email: kouakou@insa-toulouse.fr>, llegregam <legregam@insa-toulouse.fr>, Pierre Millard <millard@insa-toulouse.fr>, sgsokol <sokol@insa-toulouse.fr
Requires-Python: >=3.10
Classifier: Programming Language :: Python :: 3
Classifier: Programming Language :: Python :: 3.10
Classifier: Programming Language :: Python :: 3.11
Classifier: Programming Language :: Python :: 3.12
Requires-Dist: influx-si (>=7.2.4,<8.0.0)
Requires-Dist: numpy (>=1.24.0,<2.0.0)
Requires-Dist: openpyxl (>=3.1.5,<4.0.0)
Requires-Dist: pandas (>=2.1.4,<3.0.0)
Requires-Dist: plotly (>=5.23.0,<6.0.0)
Requires-Dist: sess-i (>=0.2.1,<0.3.0)
Requires-Dist: streamlit (>=1.41,<2.0)
